LICENSE.txt
README.md
setup.py
hyperapi_colombia/__init__.py
hyperapi_colombia/hyperapi.py
hyperapi_colombia.egg-info/PKG-INFO
hyperapi_colombia.egg-info/SOURCES.txt
hyperapi_colombia.egg-info/dependency_links.txt
hyperapi_colombia.egg-info/requires.txt
hyperapi_colombia.egg-info/top_level.txt