Metadata-Version: 2.1
Name: hyperapi_colombia
Version: 0.0.4
Summary: HyperAPI powerful api for image and spectrum processing.
Home-page: https://github.com/HyperCorn/HyperAPI-Python-Client
Download-URL: https://github.com/HyperCorn/HyperAPI-Python-Client/releases/tag/0.0.4
Author: HyperCorn
Author-email: hypercorncordoba@gmail.com
Keywords: IMAGES,SPECTRUMS,CROPS
Classifier: Development Status :: 5 - Production/Stable
Classifier: Intended Audience :: Developers
Classifier: License :: OSI Approved :: MIT License
Classifier: Programming Language :: Python :: 3.8
Classifier: Programming Language :: Python :: 3.9
Classifier: Programming Language :: Python :: 3.10
Classifier: Programming Language :: Python :: 3.11
Classifier: Programming Language :: Python :: 3.12
License-File: LICENSE.txt
Requires-Dist: requests
